libenum/__init__.py
tests/__init__.py
tests/test_classdict.py
tests/test_metaclass.py
libenum-1.0.2.dist-info/LICENSE
libenum-1.0.2.dist-info/METADATA
libenum-1.0.2.dist-info/WHEEL
libenum-1.0.2.dist-info/top_level.txt
libenum-1.0.2.dist-info/RECORD
