Metadata-Version: 2.1
Name: libenum
Version: 1.0.2
Summary: A small enum package
Home-page: https://github.com/caser789/libenum
Author: Xue Jiao
Author-email: jiao.xuejiao@gmail.com
License: MIT
Platform: any
Classifier: Programming Language :: Python :: 2
Classifier: License :: OSI Approved :: MIT License
Classifier: Operating System :: OS Independent
Requires-Dist: six
